{
    "SearchCatagories": {
        "activity": [
            "CMIP5"
        ],
        "product": [
            "output1",
            "output2",
            "restricted",
            "unsolicited"
        ],
        "organization": [
            "BCC",
            "BNU",
            "CCCMA",
            "CMCC",
            "CNRM-CERFACS",
            "COLA-CFS",
            "CSIRO-BOM",
            "CSIRO-QCCCE",
            "FIO",
            "ICHEC",
            "INM",
            "INPE",
            "IPSL",
            "LASG-CESS",
            "LASG-IAP",
            "MIROC",
            "MOHC",
            "MPI-M",
            "MRI",
            "NASA-GISS",
            "NASA-GMAO",
            "NCAR",
            "NCC",
            "NCEP",
            "NICAM",
            "NIMR-KMA",
            "NOAA-GFDL",
            "NSF-DOE-NCAR",
            "SMHI",
            "UNSW"
        ],
        "model": [
            "ACCESS1.0",
            "ACCESS1.3",
            "BCC - CSM1.1",
            "BCC - CSM1.1(m)",
            "BNU - ESM",
            "CCSM4",
            "CESM1(BGC)",
            "CESM1(CAM5)",
            "CESM1(CAM5.1, FV2)",
            "CESM1(FASTCHEM)",
            "CESM1(WACCM)",
            "CFSv2 - 2011",
            "CMCC - CESM",
            "CMCC - CM",
            "CMCC - CMS",
            " CNRM - CM5",
            "CNRM - CM5 - 2",
            "CSIRO - Mk3.6.0",
            "CSIRO - Mk3L - 1 - 2",
            "CanAM4",
            "CanCM4",
            "CanESM2",
            "EC - EARTH",
            "FGOALS - g2",
            "FGOALS - gl",
            "FGOALS - s2",
            "FIO - ESM",
            "GEOS - 5",
            "GFDL - CM2.1",
            "GFDL - CM3",
            "GFDL - ESM2G",
            "GFDL - ESM2M",
            "GFDL - HIRAM - C180",
            "GFDL - HIRAM - C360",
            "GISS - E2 - H",
            "GISS - E2 - H - CC",
            "GISS - E2 - R",
            "GISS - E2 - R - CC",
            "HadCM3",
            "HadGEM2 - A",
            "HadGEM2 - AO",
            "HadGEM2 - CC ",
            "HadGEM2 - ES",
            "INM - CM4",
            "IPSL - CM5A - LR",
            "IPSL - CM5A - MR",
            "IPSL - CM5B - LR",
            "MIROC - ESM",
            "MIROC - ESM - CHEM",
            "MIROC4h",
            "MIROC5",
            "MPI - ESM - LR",
            "MPI - ESM - MR",
            "MPI - ESM - P",
            "MRI - AGCM3.2H",
            "MRI - AGCM3.2S",
            "MRI - CGCM3",
            "MRI - ESM1",
            "NICAM - 09",
            "NorESM1 - M",
            "NorESM1 - ME"
        ],
        "experiment": [
            "abrupt4xCO2",
            "amip",
            "amip4K",
            "amip4xCO2",
            "amipFuture",
            "aqua4K",
            "aqua4xCO2",
            "aquaControl",
            "decadal1959",
            "decadal1960",
            "decadal1961",
            "decadal1962",
            "decadal1963",
            "decadal1964",
            "decadal1965",
            "decadal1966",
            "decadal1967",
            "decadal1968",
            "decadal1969",
            "decadal1970",
            "decadal1971",
            "decadal1972",
            "decadal1973",
            "decadal1974",
            "decadal1975",
            "decadal1976",
            "decadal1977",
            "decadal1978",
            "decadal1979",
            "decadal1980",
            "decadal1981",
            "decadal1982",
            "decadal1983",
            "decadal1984",
            "decadal1985",
            "decadal1986",
            "decadal1987",
            "decadal1988",
            "decadal1989",
            "decadal1990",
            "decadal1991",
            "decadal1992",
            "decadal1993",
            "decadal1994",
            "decadal1995",
            "decadal1996",
            "decadal1997",
            "decadal1998",
            "decadal1999",
            "decadal2000",
            "decadal2001",
            "decadal2002",
            "decadal2003",
            "decadal2004",
            "decadal2005",
            "decadal2006",
            "decadal2007",
            "decadal2008",
            "decadal2009",
            "decadal2010",
            " decadal2011",
            "decadal2012",
            "esmControl",
            "esmFdbk1",
            "esmFdbk2",
            "esmFixClim1",
            "esmFixClim2",
            "esmHistorical",
            "esmrcp85",
            "historical",
            "historicalExt",
            "historicalGHG",
            "historicalMisc",
            "historicalNat",
            "lgm",
            "midHolocene",
            "noVolc1960",
            "noVolc1965",
            "noVolc1970",
            "noVolc1975",
            "noVolc1985",
            "noVolc1990",
            "noVolc1995",
            "noVolc2000",
            "noVolc2005",
            "past1000",
            "piControl",
            "rcp26",
            "rcp45",
            "rcp60",
            "rcp85",
            "sst2030",
            "sst2090",
            "sst2090rcp45",
            "sstClim",
            "sstClim4xCO2",
            "sstClimAerosol",
            "sstClimSulfate",
            "volcIn2010"
        ],
        "frequency": [
            "3hr",
            "6hr",
            "day",
            "fx",
            "mon",
            "monClim",
            "subhr",
            "yr"
        ],
        "modeling_realm": [
            "aerosol",
            "atmos",
            "land",
            "landIce",
            "ocean",
            "seaIce"
        ],
        "variable_name": [
            "agessc",
            "albisccp",
            "areacella",
            "areacello",
            "bmelt",
            "burntArea",
            "cCwd",
            "cLeaf",
            "cLitter",
            "cMisc",
            "cProduct",
            "cRoot",
            "cSoil",
            "cSoilFast",
            "cSoilMedium",
            "cSoilSlow",
            "cVeg",
            "cWood",
            "ccb",
            "cct",
            "cfc11",
            "ch4",
            "chl",
            "chlcalc",
            "chldiat",
            "chldiaz",
            "chlpico",
            "ci",
            "cl",
            "clcalipso",
            "clhcalipso",
            "cli",
            "clic",
            "clis",
            "clisccp",
            "clivi",
            "cllcalipso",
            "clmcalipso",
            "clt",
            "cltcalipso",
            "cltisccp",
            "clw",
            "clwc",
            "clws",
            "clwvi",
            "co2",
            "co3",
            "co3satarag",
            "co3satcalc",
            "deptho",
            "dfe",
            "dissic",
            "dissoc",
            "divice",
            "dpco2",
            "epc100",
            "epcalc100",
            "epfe100",
            "epsi100",
            "evap",
            "evspsbl",
            "expc",
            "expcalc",
            "expcfe",
            "expsi",
            "fFire",
            "fLitterSoil",
            "fLuc",
            "fVegLitter",
            "fbddtalk",
            "fbddtdic",
            "fbddtdife",
            "fbddtdin",
            "fbddtdip",
            "fbddtdisi",
            "fddtalk",
            "fddtdic",
            "fddtdife",
            "fddtdin",
            "fddtdip",
            "fddtdisi",
            "fgco2",
            "fgo2",
            "frn",
            "gpp",
            "grCongel",
            "grFrazil",
            "h2o",
            "hflssi",
            "hfss",
            "hfssi",
            "hur",
            "hurs",
            "hus",
            "huss",
            "intdic",
            "intpbsi",
            "intpcalc",
            "intpcalcite",
            "intpdiat",
            "intpdiaz",
            "intpn2",
            "intpnitrate",
            "intpp",
            "intppico",
            "lai",
            "lwsnl",
            "masso",
            "mc",
            "mrfso",
            "mrlsl",
            "mrro",
            "mrros",
            "mrso",
            "mrsofc",
            "mrsos",
            "msftbarot",
            "msftmyz",
            "msftmyzba",
            "n2o",
            "nbp",
            "nh4",
            "no3",
            "npp",
            "nppLeaf",
            "nppRoot",
            "nppWood",
            "o2",
            "o2min",
            "od550aer",
            "omlmax",
            "orog",
            "ph",
            "phyc",
            "phyfe",
            "phyn",
            "phyp",
            "phypico",
            "physi",
            "po4",
            "pr",
            "prc",
            "prsn",
            "prveg",
            "prw",
            "ps",
            "psl",
            "rGrowth",
            "rMaint",
            "ra",
            "reffclic",
            "reffclis",
            "reffclwc",
            "reffclws",
            "reffrains",
            "rlds",
            "rldscs",
            "rldssi",
            "rlus",
            "rlussi",
            "rlut",
            "rlutcs",
            "rsds",
            "rsdscs",
            "rsdssi",
            "rsdt",
            "rsntds",
            "rsus",
            "rsuscs",
            "rsut",
            "rsutcs",
            "rtmt",
            "sci",
            "sfcWind",
            "sftgif",
            "sftlf",
            "sftof",
            "si",
            "sic",
            "sit",
            "snc",
            "snoToIce",
            "snomelt",
            "snw",
            "so",
            "soga",
            "sootsn",
            "sos",
            "spco2",
            "strairx",
            "strairy",
            "streng",
            "strocnx",
            "strocny",
            "ta",
            "ta700",
            "talk",
            "tas",
            "tasmax",
            "tasmin",
            "tauu",
            "tauuo",
            "tauv",
            "tauvo",
            "thetao",
            "thetaoga",
            "thkcello",
            "tmelt",
            "tnhus",
            "tnhusa",
            "tnhusc",
            "tnhusd",
            "tnhusmp",
            "tnhusscpbl",
            "tnt",
            "tntc",
            "tntmp",
            "tntr",
            "tntscpbl",
            "tos",
            "tossq",
            "tran",
            "tro3",
            "ts",
            "tsice",
            "tsl",
            "ua",
            "umo",
            "uo",
            "usi",
            "va",
            "vmo",
            "vo",
            "volcello",
            "vsi",
            "wap",
            "wmo",
            "wmosq",
            "zg",
            "zo2min",
            "zooc",
            "zos",
            "zosga",
            "zossga",
            "zossq",
            "zostoga",
            "zsatarag",
            "zsatcalc"
        ],
        "ensemble": [
            "r0i0p0",
            "r10i1p1",
            "r10i2p1",
            "r1i1p1",
            "r1i1p10",
            "r1i1p11",
            "r1i1p12",
            "r1i1p13",
            "r1i1p14",
            "r1i1p15",
            "r1i1p16",
            "r1i1p17",
            "r1i1p2",
            "r1i1p3",
            "r1i2p1",
            "r1i2p2",
            "r2i1p1",
            "r2i1p10",
            "r2i1p11",
            "r2i1p12",
            "r2i1p13",
            "r2i1p14",
            "r2i1p16",
            "r2i1p17",
            "r2i2p1",
            "r3i1p1",
            "r3i1p10",
            "r3i1p11",
            "r3i1p13",
            "r3i1p14",
            "r3i1p16",
            "r3i1p17",
            "r3i2p1",
            "r4i1p1",
            "r4i1p10",
            "r4i1p11",
            "r4i1p12",
            "r4i1p14",
            "r4i1p15",
            "r4i1p16",
            "r4i1p17",
            "r4i2p1",
            "r5i1p1",
            "r5i2p1",
            "r6i1p1",
            "r6i1p10",
            "r6i1p11",
            "r6i1p12",
            "r6i1p13",
            "r6i1p14",
            "r6i1p15",
            "r6i1p16",
            "r6i1p17",
            "r6i2p1",
            "r7i1p1",
            "r7i2p1",
            "r8i1p1",
            "r8i2p1",
            "r9i1p1",
            "r9i2p1"
        ]
    }
}